{
    "Alice": {
        "scores": [
            {
                "theme": "Python",
                "score": 80,
                "date": "2024-04-15"
            },
            {
                "theme": "Histoire",
                "score": 60,
                "date": "2024-04-15"
            }
        ]
    },
    "Bob": {
        "scores": [
            {
                "theme": "Python",
                "score": 100,
                "date": "2024-04-15"
            }
        ]
    },
    "royal_blood": {
        "scores": [
            {
                "theme": null,
                "score": 80,
                "date": "2025-03-29"
            },
            {
                "theme": null,
                "score": 80,
                "date": "2025-03-29"
            }
        ]
    },
    "eve": {
        "scores": [
            {
                "theme": null,
                "score": 10,
                "date": "2025-03-29"
            }
        ]
    },
    "Redteamer": {
        "scores": [
            {
                "theme": null,
                "score": 60,
                "date": "2025-03-29"
            }
        ]
    },
    "hacker_pro": {
        "scores": [
            {
                "theme": null,
                "score": 60,
                "date": "2025-03-29"
            }
        ]
    },
    "pablo_escobar": {
        "scores": [
            {
                "theme": null,
                "score": 50,
                "date": "2025-03-29"
            },
            {
                "theme": null,
                "score": 100,
                "date": "2025-03-29"
            }
        ]
    }
}